fpy2/__init__.py
fpy2/decorator.py
fpy2/env.py
fpy2/fpc_context.py
fpy2/function.py
fpy2/ops.py
fpy2/primitive.py
fpy2/runner.py
fpy2/types.py
fpy2/analysis/__init__.py
fpy2/analysis/context_infer.py
fpy2/analysis/define_use.py
fpy2/analysis/defs.py
fpy2/analysis/live_vars.py
fpy2/analysis/purity.py
fpy2/analysis/reachability.py
fpy2/analysis/reaching_defs.py
fpy2/analysis/syntax_check.py
fpy2/analysis/type_infer.py
fpy2/ast/__init__.py
fpy2/ast/formatter.py
fpy2/ast/fpyast.py
fpy2/ast/visitor.py
fpy2/backend/__init__.py
fpy2/backend/backend.py
fpy2/backend/fpc.py
fpy2/backend/cpp/__init__.py
fpy2/backend/cpp/compiler.py
fpy2/backend/cpp/ops.py
fpy2/backend/cpp/types.py
fpy2/backend/cpp/utils.py
fpy2/frontend/__init__.py
fpy2/frontend/fpc.py
fpy2/frontend/parser.py
fpy2/interpret/__init__.py
fpy2/interpret/default.py
fpy2/interpret/interpreter.py
fpy2/libraries/__init__.py
fpy2/libraries/base.py
fpy2/libraries/core.py
fpy2/libraries/eft.py
fpy2/libraries/matrix.py
fpy2/libraries/metrics.py
fpy2/libraries/vector.py
fpy2/number/__init__.py
fpy2/number/context.py
fpy2/number/efloat.py
fpy2/number/exponential.py
fpy2/number/fixed.py
fpy2/number/globals.py
fpy2/number/gmp.py
fpy2/number/ieee754.py
fpy2/number/mp_fixed.py
fpy2/number/mp_float.py
fpy2/number/mpb_fixed.py
fpy2/number/mpb_float.py
fpy2/number/mps_float.py
fpy2/number/native.py
fpy2/number/number.py
fpy2/number/real.py
fpy2/number/round.py
fpy2/number/sm_fixed.py
fpy2/rewrite/__init__.py
fpy2/rewrite/applier.py
fpy2/rewrite/matcher.py
fpy2/rewrite/pattern.py
fpy2/rewrite/rewrite.py
fpy2/rewrite/subst.py
fpy2/strategies/__init__.py
fpy2/strategies/loop_split.py
fpy2/strategies/loop_unroll.py
fpy2/strategies/simple.py
fpy2/transform/__init__.py
fpy2/transform/const_fold.py
fpy2/transform/const_prop.py
fpy2/transform/copy_propagate.py
fpy2/transform/dead_code.py
fpy2/transform/for_bundling.py
fpy2/transform/for_unpack.py
fpy2/transform/for_unroll.py
fpy2/transform/func_inline.py
fpy2/transform/func_update.py
fpy2-0.1.1.dist-info/licenses/LICENSE
fpy2-0.1.1.dist-info/METADATA
fpy2-0.1.1.dist-info/WHEEL
fpy2-0.1.1.dist-info/top_level.txt
fpy2-0.1.1.dist-info/RECORD
