Metadata-Version: 2.4
Name: fpy2
Version: 0.1.1
Summary: An embedded DSL for numerical computing
Author-email: Brett Saiki <bsaiki@cs.washington.edu>
License-Expression: MIT
Project-URL: Homepage, https://github.com/bksaiki/fpy
Project-URL: Issues, https://github.com/bksaiki/fpy/issues
Project-URL: Documentation, https://fpy.readthedocs.io/
Classifier: Programming Language :: Python :: 3
Classifier: Operating System :: OS Independent
Requires-Python: >=3.11
License-File: LICENSE
Requires-Dist: titanfp==0.1.1
Requires-Dist: gmpy2==2.2
Requires-Dist: matplotlib
Provides-Extra: dev
Requires-Dist: hypothesis==6.135; extra == "dev"
Requires-Dist: mypy; extra == "dev"
Requires-Dist: ruff; extra == "dev"
Requires-Dist: build; extra == "dev"
Requires-Dist: twine; extra == "dev"
Requires-Dist: sphinx; extra == "dev"
Requires-Dist: sphinx-rtd-theme; extra == "dev"
Requires-Dist: sphinx-pyproject; extra == "dev"
Dynamic: license-file
